LICENSE
faker_security/providers.py
faker_security-0.5.0.dist-info/LICENSE
faker_security-0.5.0.dist-info/WHEEL
faker_security-0.5.0.dist-info/METADATA
faker_security-0.5.0.dist-info/RECORD
