Metadata-Version: 2.1
Name: faker-security
Version: 0.5.0
Summary: Faker provider for security related data
Home-page: https://github.com/snyk/faker-security
License: Apache-2.0
Keywords: faker
Author: Snyk Security R&D
Author-email: security-engineering@snyk.io
Requires-Python: >=3.8,<4.0
Classifier: License :: OSI Approved :: Apache Software License
Classifier: Programming Language :: Python :: 3
Classifier: Programming Language :: Python :: 3.8
Classifier: Programming Language :: Python :: 3.9
Classifier: Programming Language :: Python :: 3.10
Classifier: Programming Language :: Python :: 3.11
Requires-Dist: faker (>=8.2.1)
Project-URL: Repository, https://github.com/snyk/faker-security
